Workbook

Sheet Word Vectors Twitter
A1: word | B1: dim_0 | C1: dim_1 | D1: dim_2 | E1: dim_3 | F1: dim_4 | G1: dim_5 | H1: dim_6 | I1: dim_7 | J1: dim_8 | K1: dim_9 | L1: dim_10 | M1: dim_11 | N1: dim_12 | O1: dim_13 | P1: dim_14 | Q1: dim_15 | R1: dim_16 | S1: dim_17 | T1: dim_18 | U1: dim_19 | V1: dim_20 | W1: dim_21 | X1: dim_22 | Y1: dim_23 | Z1: dim_24
A2: follow | B2: 0.0033407 | C2: 0.91533 | D2: -1.2207 | E2: -0.45773 | F2: -0.59682 | G2: -0.64277 | H2: 1.0497 | I2: 1.7013 | J2: -1.3643 | K2: 0.3601 | L2: -0.25219 | M2: -0.14811 | N2: -3.8711 | O2: -1.0949 | P2: -1.3944 | Q2: 0.22114 | R2: -0.76684 | S2: -2.0907 | T2: -1.0099 | U2: 0.20968 | V2: -0.27403 | W2: -1.8368 | X2: -0.4521 | Y2: 0.8915 | Z2: -1.0369
A3: know | B3: 0.3026 | C3: 0.69964 | D3: -0.0034578 | E3: -0.058919 | F3: -0.68751 | G3: -0.14206 | H3: 1.9477 | I3: 0.012731 | J3: -0.51457 | K3: 0.17647 | L3: -0.78809 | M3: 0.5208 | N3: -5.5365 | O3: -0.58156 | P3: 0.044223 | Q3: 0.25819 | R3: 0.46792 | S3: -0.81097 | T3: 0.11121 | U3: -0.16901 | V3: 1.1741 | W3: 0.48617 | X3: -0.02715 | Y3: 0.62826 | Z3: -0.27193
A4: back | B4: -0.74355 | C4: 0.715 | D4: -0.1593 | E4: -0.28136 | F4: -0.736 | G4: -0.17702 | H4: 1.0432 | I4: 0.62863 | J4: -1.0324 | K4: 0.44264 | L4: -0.11356 | M4: 0.30086 | N4: -4.7917 | O4: -0.22962 | P4: -0.21154 | Q4: -0.14965 | R4: -0.31582 | S4: -1.3908 | T4: -0.736 | U4: -0.46094 | V4: -0.13124 | W4: -0.96047 | X4: 1.2604 | Y4: 0.2479 | Z4: -0.44585
A5: people | B5: 0.61531 | C5: 0.40895 | D5: -0.34224 | E5: 0.21094 | F5: -0.046403 | G5: 0.29744 | H5: 1.9485 | I5: -0.91247 | J5: -0.85772 | K5: 0.57293 | L5: -0.99537 | M5: -0.15858 | N5: -5.4328 | O5: 0.11578 | P5: -0.27031 | Q5: 0.35207 | R5: 0.16624 | S5: -0.91364 | T5: 0.6933 | U5: -0.65035 | V5: 0.77353 | W5: -0.087782 | X5: -0.43228 | Y5: -0.99982 | Z5: -0.68077
A6: really | B6: -0.08943 | C6: 0.22163 | D6: 0.18244 | E6: -0.83415 | F6: -0.44891 | G6: 0.47993 | H6: 2.1459 | I6: -0.45866 | J6: -0.71512 | K6: -0.25822 | L6: -0.40632 | M6: 0.80012 | N6: -5.3547 | O6: -0.75984 | P6: 0.12148 | Q6: 0.24563 | R6: 0.2095 | S6: -0.44553 | T6: -0.01365 | U6: -0.44779 | V6: 0.86121 | W6: 0.59802 | X6: 0.11607 | Y6: 0.69295 | Z6: -0.39653
A7: think | B7: 0.32648 | C7: 0.48392 | D7: 0.13726 | E7: -0.3465 | F7: -0.80444 | G7: 0.13492 | H7: 1.8195 | I7: -0.41097 | J7: -0.55192 | K7: -0.041287 | L7: -0.43644 | M7: 0.65345 | N7: -5.4586 | O7: -0.58895 | P7: 0.071544 | Q7: 0.19618 | R7: 0.38752 | S7: -0.59623 | T7: 0.091468 | U7: -0.52565 | V7: 0.77938 | W7: 0.68852 | X7: -0.12746 | Y7: 0.1726 | Z7: -0.60569
A8: would | B8: -0.1093 | C8: 0.31885 | D8: -0.30186 | E8: -0.6054 | F8: -0.97979 | G8: -0.61332 | H8: 1.7117 | I8: -0.73405 | J8: -0.70542 | K8: -0.44535 | L8: 0.57517 | M8: 0.60497 | N8: -5.6804 | O8: -0.42542 | P8: -0.18938 | Q8: 0.093922 | R8: 0.46316 | S8: -0.75234 | T8: 0.33293 | U8: -0.76565 | V8: 0.54216 | W8: 0.53068 | X8: 0.35644 | Y8: 0.28121 | Z8: -0.38527
A9: please | B9: -0.32909 | C9: 0.40221 | D9: -0.81 | E9: -0.37379 | F9: -0.91075 | G9: -1.4961 | H9: 1.7134 | I9: 0.90296 | J9: -0.93052 | K9: 0.23089 | L9: -0.30272 | M9: -0.23206 | N9: -4.2977 | O9: -0.94941 | P9: -0.27274 | Q9: 0.1943 | R9: -0.19176 | S9: -1.6868 | T9: -0.40934 | U9: -0.53334 | V9: -0.27725 | W9: -0.86553 | X9: -0.16371 | Y9: 0.89115 | Z9: -0.74183
A10: right | B10: -0.43876 | C10: 0.095692 | D10: 0.0030075 | E10: -0.13195 | F10: -0.087741 | G10: -0.036863 | H10: 1.7566 | I10: -0.47702 | J10: -0.46528 | K10: 0.46637 | L10: -0.87605 | M10: 0.80857 | N10: -5.1846 | O10: -0.11673 | P10: 0.76945 | Q10: 0.12328 | R10: 0.073833 | S10: -0.88051 | T10: -0.22639 | U10: -0.17336 | V10: 0.21476 | W10: 0.17998 | X10: 0.80019 | Y10: 0.30652 | Z10: 0.159
A11: twitter | B11: 1.6952 | C11: 0.42694 | D11: 0.14433 | E11: -0.16535 | F11: 1.0463 | G11: -0.029846 | H11: 0.33623 | I11: 1.5362 | J11: -0.58481 | K11: 0.50349 | L11: -0.50595 | M11: -0.91136 | N11: -3.8011 | O11: -0.8685 | P11: -0.13552 | Q11: 0.97055 | R11: -0.13545 | S11: -0.29825 | T11: -1.2837 | U11: -0.63245 | V11: 0.44748 | W11: -0.92231 | X11: -0.4138 | Y11: 0.20287 | Z11: -0.33432
A12: hate | B12: 0.66523 | C12: 0.73776 | D12: 0.022958 | E12: 0.13177 | F12: -0.7063 | G12: 0.64642 | H12: 2.1068 | I12: -0.56058 | J12: -0.70352 | K12: 0.83807 | L12: -1.1425 | M12: -0.092725 | N12: -4.4378 | O12: -0.76222 | P12: 0.18249 | Q12: 0.72472 | R12: 0.0060011 | S12: -0.73652 | T12: 0.0023592 | U12: -0.3483 | V12: 0.6523 | W12: 1.0148 | X12: 0.19504 | Y12: -0.31584 | Z12: -0.50971
A13: thanks | B13: -0.80095 | C13: 0.82385 | D13: -0.28273 | E13: -0.10817 | F13: -0.55175 | G13: -0.72222 | H13: 1.6159 | I13: 0.9797 | J13: -1.001 | K13: 0.26292 | L13: -0.68467 | M13: 0.50623 | N13: -3.8982 | O13: -0.56209 | P13: 0.43343 | Q13: -0.66157 | R13: 0.86205 | S13: -1.0689 | T13: -1.0178 | U13: 0.05931 | V13: -0.35647 | W13: -0.43121 | X13: -1.1485 | Y13: 1.3683 | Z13: -0.72813
... A1001: photographer | B1001: -0.81734 | C1001: -0.29904 | D1001: 0.087551 | E1001: -0.80352 | F1001: 1.0755 | G1001: -1.1484 | H1001: 0.52482 | I1001: -0.0069553 | J1001: 0.59713 | K1001: -0.7343 | L1001: 0.47216 | M1001: 0.6439 | N1001: -2.302 | O1001: -0.64404 | P1001: 0.015007 | Q1001: 0.078171 | R1001: 0.9215 | S1001: -0.26196 | T1001: 0.16341 | U1001: 0.13301 | V1001: 0.1996 | W1001: -0.57648 | X1001: -1.4477 | Y1001: -1.2633 | Z1001: -0.81482

Sheet Word Vectors Wiki
A1: word | B1: dim_0 | C1: dim_1 | D1: dim_2 | E1: dim_3 | F1: dim_4 | G1: dim_5 | H1: dim_6 | I1: dim_7 | J1: dim_8 | K1: dim_9 | L1: dim_10 | M1: dim_11 | N1: dim_12 | O1: dim_13 | P1: dim_14 | Q1: dim_15 | R1: dim_16 | S1: dim_17 | T1: dim_18 | U1: dim_19 | V1: dim_20 | W1: dim_21 | X1: dim_22 | Y1: dim_23 | Z1: dim_24 | AA1: dim_25 | AB1: dim_26 | AC1: dim_27 | AD1: dim_28 | AE1: dim_29 | AF1: dim_30 | AG1: dim_31 | AH1: dim_32 | AI1: dim_33 | AJ1: dim_34 | AK1: dim_35 | AL1: dim_36 | AM1: dim_37 | AN1: dim_38 | AO1: dim_39 | AP1: dim_40 | AQ1: dim_41 | AR1: dim_42 | AS1: dim_43 | AT1: dim_44 | AU1: dim_45 | AV1: dim_46 | AW1: dim_47 | AX1: dim_48 | AY1: dim_49
A2: would | B2: 0.7619 | C2: -0.29773 | D2: 0.51396 | E2: -0.13303 | F2: 0.24156 | G2: 0.066799 | H2: -0.54084 | I2: 0.2071 | J2: -0.28225 | K2: -0.11638 | L2: 0.21666 | M2: 0.54908 | N2: -0.36744 | O2: -0.10543 | P2: 0.81567 | Q2: 1.1743 | R2: 0.56055 | S2: -0.3345 | T2: 0.099767 | U2: -0.87465 | V2: 0.12229 | W2: -0.18532 | X2: 0.086783 | Y2: -0.36343 | Z2: 0.008002 | AA2: -2.2268 | AB2: -0.20079 | AC2: -0.10313 | AD2: 0.24318 | AE2: -0.39819 | AF2: 3.7136 | AG2: 0.59088 | AH2: -1.1013 | AI2: -0.25292 | AJ2: 0.0057067 | AK2: -0.60475 | AL2: 0.35965 | AM2: -0.059581 | AN2: -0.029059 | AO2: -0.3989 | AP2: -0.52631 | AQ2: 0.12436 | AR2: 0.13609 | AS2: 0.12699 | AT2: -0.23032 | AU2: -0.044567 | AV2: -0.6545 | AW2: 0.43088 | AX2: -0.22768 | AY2: 0.4026
A3: first | B3: -0.14168 | C3: 0.41108 | D3: -0.31227 | E3: 0.16633 | F3: 0.26124 | G3: 0.45708 | H3: -1.2001 | I3: 0.014923 | J3: -0.22779 | K3: -0.16937 | L3: 0.34633 | M3: -0.12419 | N3: -0.65711 | O3: 0.29226 | P3: 0.62407 | Q3: -0.57916 | R3: -0.33947 | S3: -0.22046 | T3: -1.4832 | U3: 0.28958 | V3: 0.081396 | W3: -0.21696 | X3: 0.0056613 | Y3: -0.054199 | Z3: 0.098504 | AA3: -1.5874 | AB3: -0.22867 | AC3: -0.62957 | AD3: -0.39542 | AE3: -0.080841 | AF3: 3.5949 | AG3: -0.16872 | AH3: -0.39024 | AI3: 0.026912 | AJ3: 0.52646 | AK3: -0.022844 | AL3: 0.63289 | AM3: 0.62702 | AN3: -0.22171 | AO3: -0.45045 | AP3: -0.14998 | AQ3: -0.27723 | AR3: -0.46658 | AS3: -0.44268 | AT3: -0.43691 | AU3: 0.38455 | AV3: 0.1369 | AW3: -0.25424 | AX3: 0.017821 | AY3: -0.1489
A4: year | B4: -0.098793 | C4: 0.26983 | D4: 0.35304 | E4: -0.10727 | F4: -0.015183 | G4: 0.053398 | H4: -1.0824 | I4: -0.53005 | J4: 0.0095416 | K4: 0.070428 | L4: -0.08925 | M4: -0.62666 | N4: -0.52662 | O4: -0.56571 | P4: 1.8044 | Q4: 0.01686 | R4: -0.44871 | S4: -0.04146 | T4: -1.1136 | U4: 0.17488 | V4: 0.49561 | W4: -0.38238 | X4: 0.30185 | Y4: -0.70675 | Z4: -0.35891 | AA4: -1.5164 | AB4: -0.024403 | AC4: -0.54107 | AD4: -0.36163 | AE4: 0.52803 | AF4: 3.6553 | AG4: 0.71214 | AH4: -0.16995 | AI4: 0.36368 | AJ4: 0.3399 | AK4: -0.48186 | AL4: 0.10936 | AM4: 0.61428 | AN4: 0.15697 | AO4: -0.70716 | AP4: -1.2359 | AQ4: -0.014258 | AR4: 0.095588 | AS4: -0.30634 | AT4: -0.49741 | AU4: -0.049394 | AV4: -0.16697 | AW4: 0.11972 | AX4: -0.37511 | AY4: 0.098348
A5: people | B5: 0.95281 | C5: -0.20608 | D5: 0.55618 | E5: -0.46323 | F5: 0.73354 | G5: 0.029137 | H5: -0.19367 | I5: -0.090066 | J5: -0.22958 | K5: -0.19058 | L5: -0.34857 | M5: -1.0231 | N5: 0.743 | O5: -0.5489 | P5: 0.88484 | Q5: -0.14051 | R5: 0.0040139 | S5: 0.58448 | T5: 0.10767 | U5: -0.44657 | V5: -0.43205 | W5: 0.9868 | X5: 0.78288 | Y5: 0.51513 | Z5: 0.85788 | AA5: -1.7713 | AB5: -0.88259 | AC5: -0.59728 | AD5: 0.084934 | AE5: -0.48112 | AF5: 3.9678 | AG5: 0.8893 | AH5: -0.27064 | AI5: -0.44094 | AJ5: -0.26213 | AK5: 0.085597 | AL5: 0.022099 | AM5: -0.58376 | AN5: 0.10908 | AO5: 0.77973 | AP5: -0.95447 | AQ5: 0.40482 | AR5: 0.8941 | AS5: 0.65251 | AT5: 0.39858 | AU5: 0.20884 | AV5: -1.3281 | AW5: -0.10882 | AX5: -0.22822 | AY5: -0.46303
A6: government | B6: 0.38797 | C6: -1.0825 | D6: 0.45025 | E6: -0.23341 | F6: 0.086307 | G6: -0.25721 | H6: -0.18281 | I6: -0.10037 | J6: -0.50099 | K6: -0.58361 | L6: -0.052635 | M6: -0.14224 | N6: 0.0090217 | O6: -0.38308 | P6: 0.18503 | Q6: 0.42444 | R6: 0.10611 | S6: -0.1487 | T6: 1.0801 | U6: 0.065757 | V6: 0.64552 | W6: 0.1908 | X6: -0.14561 | Y6: -0.87237 | Z6: -0.35568 | AA6: -2.435 | AB6: 0.28428 | AC6: -0.33436 | AD6: -0.56139 | AE6: 0.91404 | AF6: 4.0129 | AG6: 0.072234 | AH6: -1.2478 | AI6: -0.36592 | AJ6: -0.50236 | AK6: 0.011731 | AL6: -0.27409 | AM6: -0.50842 | AN6: -0.2584 | AO6: -0.096172 | AP6: -0.67109 | AQ6: 0.40226 | AR6: 0.27912 | AS6: -0.37317 | AT6: -0.45049 | AU6: -0.30662 | AV6: -1.6426 | AW6: 1.1936 | AX6: 0.65343 | AY6: -0.76293
A7: years | B7: 0.16962 | C7: 0.4344 | D7: -0.042106 | E7: -0.63324 | F7: -0.1278 | G7: 0.53668 | H7: -1.0662 | I7: -0.32629 | J7: -0.50079 | K7: 0.10247 | L7: -0.021968 | M7: -0.35105 | N7: -0.64153 | O7: -0.42454 | P7: 1.3836 | Q7: -0.13543 | R7: -0.24754 | S7: 0.22156 | T7: -0.65563 | U7: 0.44424 | V7: 0.17017 | W7: 0.35816 | X7: 0.56379 | Y7: -0.48044 | Z7: -0.14765 | AA7: -1.629 | AB7: -0.31308 | AC7: -0.47217 | AD7: 0.02659 | AE7: 0.47603 | AF7: 3.4619 | AG7: 0.12069 | AH7: -0.045344 | AI7: -0.47303 | AJ7: 0.28569 | AK7: -0.077584 | AL7: -0.16447 | AM7: 0.7181 | AN7: 0.2617 | AO7: -0.16841 | AP7: -1.245 | AQ7: -0.076188 | AR7: 0.17493 | AS7: 0.24507 | AT7: -0.63801 | AU7: -0.21096 | AV7: -0.49918 | AW7: -0.50108 | AX7: -0.7704 | AY7: -0.32234
A8: three | B8: 0.40545 | C8: 0.43805 | D8: 0.36237 | E8: 0.25683 | F8: 0.38254 | G8: 0.68255 | H8: -0.97853 | I8: 0.12741 | J8: -0.46129 | K8: -0.54809 | L8: -0.35384 | M8: -0.56697 | N8: -0.65756 | O8: 0.50184 | P8: 0.53248 | Q8: -0.77956 | R8: -0.089944 | S8: -0.37572 | T8: -1.1097 | U8: -0.30734 | V8: -0.022657 | W8: 0.11632 | X8: 0.67704 | Y8: -0.051499 | Z8: -0.59719 | AA8: -1.02 | AB8: 0.24289 | AC8: -0.60216 | AD8: -0.35183 | AE8: -0.54053 | AF8: 3.9844 | AG8: 0.41521 | AH8: 0.040419 | AI8: 0.26909 | AJ8: 1.1193 | AK8: 0.52924 | AL8: 0.37308 | AM8: 0.28924 | AN8: -0.14714 | AO8: 0.23566 | AP8: -0.72709 | AQ8: 0.053276 | AR8: 0.45373 | AS8: 0.20374 | AT8: -0.13384 | AU8: 0.015313 | AV8: -0.22037 | AW8: -0.15662 | AX8: -0.30289 | AY8: -0.77536
A9: city | B9: 0.43945 | C9: 0.43268 | D9: -0.36654 | E9: 0.27781 | F9: 0.062932 | G9: -0.80201 | H9: -0.93041 | I9: 0.016388 | J9: -0.5503 | K9: -0.16278 | L9: -0.40351 | M9: -1.3975 | N9: 0.32079 | O9: -0.88954 | P9: -0.18853 | Q9: 0.11516 | R9: 0.045326 | S9: 0.83002 | T9: -0.87595 | U9: 0.77653 | V9: 0.55948 | W9: 0.074721 | X9: -0.84672 | Y9: 0.4098 | Z9: -0.59774 | AA9: -2.062 | AB9: -0.15894 | AC9: 0.57979 | AD9: 0.2827 | AE9: -1.0213 | AF9: 3.2488 | AG9: 0.50029 | AH9: 0.11559 | AI9: -1.1707 | AJ9: 0.19016 | AK9: 0.36888 | AL9: -0.042018 | AM9: 0.028234 | AN9: 0.54125 | AO9: 0.8489 | AP9: -0.66711 | AQ9: 0.60799 | AR9: 0.23787 | AS9: -0.65378 | AT9: -0.7055 | AU9: 0.5165 | AV9: -1.078 | AW9: -0.71524 | AX9: 0.48402 | AY9: -0.3256
A10: country | B10: -0.13531 | C10: 0.15485 | D10: -0.07309 | E10: 0.034013 | F10: -0.054457 | G10: -0.20541 | H10: -0.60086 | I10: -0.22407 | J10: 0.42615 | K10: 0.0418 | L10: 0.1217 | M10: -0.55817 | N10: -0.08953 | O10: 0.0089426 | P10: 0.59164 | Q10: 0.34329 | R10: 0.64798 | S10: 0.30052 | T10: 0.48494 | U10: 0.16524 | V10: -0.073664 | W10: 0.31182 | X10: -0.083803 | Y10: 0.27026 | Z10: 0.10724 | AA10: -1.7704 | AB10: -0.36235 | AC10: -0.15811 | AD10: 0.060038 | AE10: 0.67873 | AF10: 4.0124 | AG10: 0.43091 | AH10: -0.26325 | AI10: 0.0561 | AJ10: -0.40052 | AK10: -0.088487 | AL10: -0.55339 | AM10: -0.17892 | AN10: -0.57372 | AO10: -0.19628 | AP10: -1.1624 | AQ10: 0.12145 | AR10: 0.55842 | AS10: -0.6194 | AT10: -0.20974 | AU10: 0.49895 | AV10: -1.0743 | AW10: -0.028168 | AX10: -0.18904 | AY10: -0.6769
A11: four | B11: 0.33375 | C11: 0.44809 | D11: 0.54759 | E11: 0.21497 | F11: 0.32637 | G11: 0.70326 | H11: -0.95872 | I11: 0.057798 | J11: -0.43454 | K11: -0.55322 | L11: -0.40482 | M11: -0.65793 | N11: -0.75076 | O11: 0.58097 | P11: 0.51968 | Q11: -0.86607 | R11: -0.10026 | S11: -0.11609 | T11: -1.2668 | U11: -0.46131 | V11: -0.10421 | W11: 0.13894 | X11: 0.70448 | Y11: -0.0040651 | Z11: -0.56479 | AA11: -0.99797 | AB11: 0.30126 | AC11: -0.53745 | AD11: -0.42073 | AE11: -0.49521 | AF11: 3.9051 | AG11: 0.43253 | AH11: 0.017059 | AI11: 0.31489 | AJ11: 1.2546 | AK11: 0.52463 | AL11: 0.46232 | AM11: 0.29622 | AN11: -0.23879 | AO11: 0.12913 | AP11: -0.75519 | AQ11: -0.065684 | AR11: 0.52592 | AS11: 0.20047 | AT11: -0.15982 | AU11: 0.18293 | AV11: -0.29966 | AW11: -0.1926 | AX11: -0.30174 | AY11: -0.80437
A12: back | B12: 0.0046218 | C12: -0.25678 | D12: 0.3532 | E12: -0.82697 | F12: 0.099033 | G12: -0.27524 | H12: -1.2297 | I12: 0.37345 | J12: -0.44635 | K12: -0.36967 | L12: -0.12421 | M12: 0.20837 | N12: -1.1801 | O12: 0.045587 | P12: 0.47457 | Q12: 0.40557 | R12: 0.046003 | S12: -0.62809 | T12: -0.70816 | U12: -0.42283 | V12: -0.24011 | W12: 0.44871 | X12: 0.14759 | Y12: -0.17298 | Z12: 0.31948 | AA12: -2.0483 | AB12: 0.43036 | AC12: 0.44567 | AD12: 0.52804 | AE12: -0.72942 | AF12: 3.5192 | AG12: 0.72008 | AH12: -0.19861 | AI12: 0.42855 | AJ12: 0.029422 | AK12: 0.15914 | AL12: -0.16062 | AM12: 0.3479 | AN12: 0.35462 | AO12: -0.53138 | AP12: -0.28746 | AQ12: 0.35596 | AR12: -0.083996 | AS12: -0.0064132 | AT12: -0.32994 | AU12: 0.055304 | AV12: 0.50614 | AW12: -0.80837 | AX12: -0.33017 | AY12: -0.62638
A13: south | B13: -0.039674 | C13: 0.47097 | D13: -0.31102 | E13: 0.38088 | F13: -0.59254 | G13: -0.38231 | H13: -0.68876 | I13: 0.15252 | J13: 0.46303 | K13: -0.9099 | L13: -0.38665 | M13: -0.82695 | N13: 0.035915 | O13: -0.93486 | P13: -0.82315 | Q13: 0.37535 | R13: 0.93198 | S13: 0.19098 | T13: -1.01 | U13: 0.59531 | V13: -0.1818 | W13: 0.34694 | X13: 0.096477 | Y13: 0.48152 | Z13: 0.19392 | AA13: -1.9725 | AB13: 0.77759 | AC13: 0.16259 | AD13: -0.68996 | AE13: -0.12239 | AF13: 3.5077 | AG13: -0.23937 | AH13: 0.12591 | AI13: 0.22983 | AJ13: 0.5462 | AK13: -0.74276 | AL13: -0.30525 | AM13: -0.19996 | AN13: -0.77648 | AO13: -0.13621 | AP13: -0.54883 | AQ13: 0.068693 | AR13: 0.88314 | AS13: -1.0529 | AT13: 0.18614 | AU13: 0.88575 | AV13: -0.43661 | AW13: -0.49549 | AX13: -0.10562 | AY13: -0.77821
... A1001: drought | B1001: -0.33153 | C1001: 0.22338 | D1001: -0.51388 | E1001: 0.40727 | F1001: -1.7321 | G1001: -0.001406 | H1001: -0.071636 | I1001: 0.49685 | J1001: 1.2796 | K1001: 0.073781 | L1001: -0.13374 | M1001: -0.50327 | N1001: 0.22312 | O1001: -0.94363 | P1001: 1.0926 | Q1001: -0.012104 | R1001: 0.35931 | S1001: -0.3504 | T1001: -0.3845 | U1001: 0.82183 | V1001: -1.686 | W1001: -0.78163 | X1001: 0.1298 | Y1001: -1.1785 | Z1001: 0.48024 | AA1001: -0.47884 | AB1001: 0.38792 | AC1001: -0.041559 | AD1001: 1.2619 | AE1001: 1.5951 | AF1001: 2.5753 | AG1001: 0.60826 | AH1001: 0.39647 | AI1001: 0.39912 | AJ1001: -0.24605 | AK1001: 1.2488 | AL1001: -0.55668 | AM1001: 0.2993 | AN1001: 0.83571 | AO1001: -0.12058 | AP1001: -2.0117 | AQ1001: 0.23152 | AR1001: 0.072356 | AS1001: 0.13795 | AT1001: 0.57238 | AU1001: 0.61066 | AV1001: 0.23533 | AW1001: 0.29491 | AX1001: -0.20523 | AY1001: -0.64847

Sheet Cosine Similarity
A1: COSINE SIMILARITY CALCULATOR
A2: Instructions: | B2: Enter two words in columns A and C (starting from row 6). Select dataset using dropdown in B3. The sheet will automatically calculate cosine similarity. Similarity ranges from -1 (opposite) to 1 (identical).
A3: Dataset: | B3: Twitter
A5: Word 1 | B5: Row Index 1 | C5: Word 2 | D5: Row Index 2 | E5: Cosine Similarity
A6: people | B6: =IF(A6="","",MATCH(A6,INDIRECT("'Word Vectors "&B3&"'!A:A"),0)-1) | C6: back | D6: =IF(C6="","",MATCH(C6,INDIRECT("'Word Vectors "&B3&"'!A:A"),0)-1) | E6: =IF(OR(A6="",C6="",NOT(ISNUMBER(B6)),NOT(ISNUMBER(D6))),"",SUMPRODUCT(INDIRECT("'Word Vectors "&B3&"'!B"&(B6+1)&":"&IF(B3="Twitter","Z","AZ")&(B6+1)),INDIRECT("'Word Vectors "&B3&"'!B"&(D6+1)&":"&IF(B3="Twitter","Z","AZ")&(D6+1)))/(SQRT(SUMPRODUCT(INDIRECT("'Word Vectors "&B3&"'!B"&(B6+1)&":"&IF(B3="Twitter","Z","AZ")&(B6+1)),INDIRECT("'Word Vectors "&B3&"'!B"&(B6+1)&":"&IF(B3="Twitter","Z","AZ")&(B6+1))))*SQRT(SUMPRODUCT(INDIRECT("'Word Vectors "&B3&"'!B"&(D6+1)&":"&IF(B3="Twitter","Z","AZ")&(D6+1)),INDIRECT("'Word Vectors "&B3&"'!B"&(D6+1)&":"&IF(B3="Twitter","Z","AZ")&(D6+1))))))
B7: =IF(A7="","",IF(ISNA(MATCH(A7,INDIRECT("'Word Vectors "&B3&"'!A:A"),0)),"Word not found",MATCH(A7,INDIRECT("'Word Vectors "&B3&"'!A:A"),0)-1)) | D7: =IF(C7="","",IF(ISNA(MATCH(C7,INDIRECT("'Word Vectors "&B3&"'!A:A"),0)),"Word not found",MATCH(C7,INDIRECT("'Word Vectors "&B3&"'!A:A"),0)-1)) | E7: =IF(OR(A7="",C7="",NOT(ISNUMBER(B7)),NOT(ISNUMBER(D7))),"",SUMPRODUCT(INDIRECT("'Word Vectors "&B3&"'!B"&(B7+1)&":"&IF(B3="Twitter","Z","AZ")&(B7+1)),INDIRECT("'Word Vectors "&B3&"'!B"&(D7+1)&":"&IF(B3="Twitter","Z","AZ")&(D7+1)))/(SQRT(SUMPRODUCT(INDIRECT("'Word Vectors "&B3&"'!B"&(B7+1)&":"&IF(B3="Twitter","Z","AZ")&(B7+1)),INDIRECT("'Word Vectors "&B3&"'!B"&(B7+1)&":"&IF(B3="Twitter","Z","AZ")&(B7+1))))*SQRT(SUMPRODUCT(INDIRECT("'Word Vectors "&B3&"'!B"&(D7+1)&":"&IF(B3="Twitter","Z","AZ")&(D7+1)),INDIRECT("'Word Vectors "&B3&"'!B"&(D7+1)&":"&IF(B3="Twitter","Z","AZ")&(D7+1))))))
A8: Tip: | B8: You can copy row 7 down to compare multiple word pairs. Change the dataset in B3 to switch between Twitter and Wiki datasets.

Sheet Instructions
A1: Instructions
A2: COSINE SIMILARITY FORMULAS
A4: This workbook contains two datasets:
A5: - Word Vectors Twitter: GloVe Twitter 25-dimensional vectors
A6: - Word Vectors Wiki: GloVe Wiki-Gigaword 50-dimensional vectors
A8: Use the dropdown on the Search tab to select which dataset to use.
A10: To calculate cosine similarity between two vectors by row index:
A12: Method 1: Direct cell reference
A13: "=SUMPRODUCT(B2:Z2,B3:Z3)/(SQRT(SUMPRODUCT(B2:Z2,B2:Z2))*SQRT(SUMPRODUCT(B3:Z3,B3:Z3)))"
A15: Method 2: Using INDEX with row numbers
A16: If row indices are in cells A1 and B1:
A17: "=SUMPRODUCT(INDEX(B:Z,A1+1,0),INDEX(B:Z,B1+1,0))/(SQRT(SUMPRODUCT(INDEX(B:Z,A1+1,0),INDEX(B:Z,A1+1,0)))*SQRT(SUMPRODUCT(INDEX(B:Z,B1+1,0),INDEX(B:Z,B1+1,0))))"
... A22: 1 = most similar, 0 = orthogonal, -1 = most dissimilar

Sheet Search
A1: TOP 10 SIMILAR WORDS FINDER
A2: Dataset: | B2: Twitter
